<?xml version="1.0" ?><patterns>		<pattern id="1997" diac="فع" canonic="فع" type="جا" cas="#" ncg="0"/>
		<pattern id="2045" diac="فعٍ" canonic="فعٍ" type="جا" cas="#" ncg="0"/>
		<pattern id="2046" diac="فعٍ" canonic="فعٍ" type="وش" cas="نك" ncg="1"/>
		<pattern id="2047" diac="فعٍ" canonic="فعٍ" type="وش" cas="نك" ncg="13"/>
		<pattern id="2205" diac="فعّ" canonic="فعّ" type="جا" cas="#" ncg="-2"/>
		<pattern id="2206" diac="فعّ" canonic="فعّ" type="جا" cas="#" ncg="0"/>
		<pattern id="2210" diac="فعٌّ" canonic="فعٌّ" type="صأ" cas="نك" ncg="1"/>
		<pattern id="2211" diac="فعَّ" canonic="فعَّ" type="صأ" cas="إض" ncg="7"/>
		<pattern id="2215" diac="فعُّ" canonic="فعُّ" type="صأ" cas="إض" ncg="1"/>
		<pattern id="2346" diac="فَع" canonic="فَع" type="جا" cas="#" ncg="-1"/>
		<pattern id="2347" diac="فَع" canonic="فَع" type="جا" cas="#" ncg="0"/>
		<pattern id="2555" diac="فَعٍ" canonic="فَعٍ" type="مفا" cas="نك" ncg="1"/>
		<pattern id="2556" diac="فَعٍ" canonic="فَعٍ" type="مفا" cas="نك" ncg="13"/>
		<pattern id="2557" diac="فَعٍ" canonic="فَعٍ" type="وش" cas="نك" ncg="1"/>
		<pattern id="2558" diac="فَعٍ" canonic="فَعٍ" type="وش" cas="نك" ncg="13"/>
		<pattern id="3050" diac="فَعّ" canonic="فَعّ" type="جا" cas="#" ncg="-1"/>
		<pattern id="3051" diac="فَعّ" canonic="فَعّ" type="جا" cas="#" ncg="-2"/>
		<pattern id="3052" diac="فَعّ" canonic="فَعّ" type="جا" cas="#" ncg="0"/>
		<pattern id="3196" diac="فَعٌّ" canonic="فَعٌّ" type="صأ" cas="نك" ncg="1"/>
		<pattern id="3197" diac="فَعٌّ" canonic="فَعٌّ" type="وش" cas="نك" ncg="1"/>
		<pattern id="3198" diac="فَعٍّ" canonic="فَعٍّ" type="صأ" cas="نك" ncg="13"/>
		<pattern id="3199" diac="فَعٍّ" canonic="فَعٍّ" type="وش" cas="نك" ncg="13"/>
		<pattern id="3200" diac="فَعَّ" canonic="فَعَّ" type="صأ" cas="إض" ncg="7"/>
		<pattern id="3201" diac="فَعَّ" canonic="فَعَّ" type="فض" cas="إض" ncg="10"/>
		<pattern id="3202" diac="فَعَّ" canonic="فَعَّ" type="فض" cas="إض" ncg="11"/>
		<pattern id="3203" diac="فَعَّ" canonic="فَعَّ" type="فض" cas="إض" ncg="12"/>
		<pattern id="3204" diac="فَعَّ" canonic="فَعَّ" type="فض" cas="إض" ncg="18"/>
		<pattern id="3205" diac="فَعَّ" canonic="فَعَّ" type="فض" cas="إض" ncg="7"/>
		<pattern id="3206" diac="فَعَّ" canonic="فَعَّ" type="فض" cas="إض" ncg="8"/>
		<pattern id="3207" diac="فَعَّ" canonic="فَعَّ" type="فض" cas="إض" ncg="9"/>
		<pattern id="3208" diac="فَعَّ" canonic="فَعَّ" type="فض" cas="نك" ncg="10"/>
		<pattern id="3209" diac="فَعَّ" canonic="فَعَّ" type="فض" cas="نك" ncg="11"/>
		<pattern id="3210" diac="فَعَّ" canonic="فَعَّ" type="فض" cas="نك" ncg="12"/>
		<pattern id="3211" diac="فَعَّ" canonic="فَعَّ" type="فض" cas="نك" ncg="18"/>
		<pattern id="3212" diac="فَعَّ" canonic="فَعَّ" type="فض" cas="نك" ncg="7"/>
		<pattern id="3213" diac="فَعَّ" canonic="فَعَّ" type="فض" cas="نك" ncg="8"/>
		<pattern id="3214" diac="فَعَّ" canonic="فَعَّ" type="فض" cas="نك" ncg="9"/>
		<pattern id="3215" diac="فَعَّ" canonic="فَعَّ" type="وش" cas="إض" ncg="7"/>
		<pattern id="3271" diac="فَعُّ" canonic="فَعُّ" type="صأ" cas="إض" ncg="1"/>
		<pattern id="3272" diac="فَعُّ" canonic="فَعُّ" type="فض" cas="إض" ncg="1"/>
		<pattern id="3273" diac="فَعُّ" canonic="فَعُّ" type="فض" cas="إض" ncg="2"/>
		<pattern id="3274" diac="فَعُّ" canonic="فَعُّ" type="فض" cas="إض" ncg="3"/>
		<pattern id="3275" diac="فَعُّ" canonic="فَعُّ" type="فض" cas="إض" ncg="4"/>
		<pattern id="3276" diac="فَعُّ" canonic="فَعُّ" type="فض" cas="إض" ncg="5"/>
		<pattern id="3277" diac="فَعُّ" canonic="فَعُّ" type="فض" cas="إض" ncg="6"/>
		<pattern id="3278" diac="فَعُّ" canonic="فَعُّ" type="فض" cas="نك" ncg="1"/>
		<pattern id="3279" diac="فَعُّ" canonic="فَعُّ" type="فض" cas="نك" ncg="2"/>
		<pattern id="3280" diac="فَعُّ" canonic="فَعُّ" type="فض" cas="نك" ncg="3"/>
		<pattern id="3281" diac="فَعُّ" canonic="فَعُّ" type="فض" cas="نك" ncg="4"/>
		<pattern id="3282" diac="فَعُّ" canonic="فَعُّ" type="فض" cas="نك" ncg="5"/>
		<pattern id="3283" diac="فَعُّ" canonic="فَعُّ" type="فض" cas="نك" ncg="6"/>
		<pattern id="3284" diac="فَعُّ" canonic="فَعُّ" type="وش" cas="إض" ncg="1"/>
		<pattern id="3288" diac="فَعِّ" canonic="فَعِّ" type="صأ" cas="إض" ncg="13"/>
		<pattern id="3289" diac="فَعِّ" canonic="فَعِّ" type="فض" cas="إض" ncg="13"/>
		<pattern id="3290" diac="فَعِّ" canonic="فَعِّ" type="فض" cas="إض" ncg="14"/>
		<pattern id="3291" diac="فَعِّ" canonic="فَعِّ" type="فض" cas="إض" ncg="15"/>
		<pattern id="3292" diac="فَعِّ" canonic="فَعِّ" type="فض" cas="إض" ncg="16"/>
		<pattern id="3293" diac="فَعِّ" canonic="فَعِّ" type="فض" cas="إض" ncg="17"/>
		<pattern id="3294" diac="فَعِّ" canonic="فَعِّ" type="فض" cas="نك" ncg="13"/>
		<pattern id="3295" diac="فَعِّ" canonic="فَعِّ" type="فض" cas="نك" ncg="14"/>
		<pattern id="3296" diac="فَعِّ" canonic="فَعِّ" type="فض" cas="نك" ncg="15"/>
		<pattern id="3297" diac="فَعِّ" canonic="فَعِّ" type="فض" cas="نك" ncg="16"/>
		<pattern id="3298" diac="فَعِّ" canonic="فَعِّ" type="فض" cas="نك" ncg="17"/>
		<pattern id="3299" diac="فَعِّ" canonic="فَعِّ" type="وش" cas="إض" ncg="13"/>
		<pattern id="3597" diac="فَُعّ" canonic="فَُعّ" type="جا" cas="#" ncg="0"/>
		<pattern id="3599" diac="فَِعّ" canonic="فَِعّ" type="جا" cas="#" ncg="0"/>
		<pattern id="3772" diac="فُعّ" canonic="فُعّ" type="جا" cas="#" ncg="-1"/>
		<pattern id="3773" diac="فُعّ" canonic="فُعّ" type="جا" cas="#" ncg="-2"/>
		<pattern id="3774" diac="فُعّ" canonic="فُعّ" type="جا" cas="#" ncg="-3"/>
		<pattern id="3775" diac="فُعّ" canonic="فُعّ" type="جا" cas="#" ncg="0"/>
		<pattern id="3783" diac="فُعٌّ" canonic="فُعٌّ" type="صأ" cas="نك" ncg="1"/>
		<pattern id="3784" diac="فُعَّ" canonic="فُعَّ" type="صأ" cas="إض" ncg="7"/>
		<pattern id="3809" diac="فُعُّ" canonic="فُعُّ" type="صأ" cas="إض" ncg="1"/>
		<pattern id="4069" diac="فِعّ" canonic="فِعّ" type="جا" cas="#" ncg="0"/>
		<pattern id="4077" diac="فِعٌّ" canonic="فِعٌّ" type="صأ" cas="نك" ncg="1"/>
		<pattern id="4078" diac="فِعَّ" canonic="فِعَّ" type="صأ" cas="إض" ncg="7"/>
		<pattern id="4101" diac="فِعُّ" canonic="فِعُّ" type="صأ" cas="إض" ncg="1"/>
		<pattern id="6" diac="آعٍ" canonic="فاعٍ" type="جا" cas="#" ncg="0"/>
		<pattern id="7" diac="آعٍ" canonic="فاعٍ" type="فا" cas="نك" ncg="1"/>
		<pattern id="8" diac="آعٍ" canonic="فاعٍ" type="فا" cas="نك" ncg="13"/>
		<pattern id="87" diac="آل" canonic="فال" type="جا" cas="#" ncg="-3"/>
		<pattern id="88" diac="آل" canonic="فال" type="جا" cas="#" ncg="0"/>
		<pattern id="90" diac="آلٌ" canonic="فالٌ" type="صأ" cas="نك" ncg="1"/>
		<pattern id="91" diac="آلَ" canonic="فالَ" type="صأ" cas="إض" ncg="7"/>
		<pattern id="97" diac="آلُ" canonic="فالُ" type="صأ" cas="إض" ncg="1"/></patterns>
